{
  "articles": [
    {
      "id": 1,
      "title": "How to Pick the Best Technology for Your Team",
      "description": "Choosing call recording software is difficult, to say the least.",
      "tag": "SALES",
      "duration": 9,
      "date": "2025-01-01T10:00:00Z",
      "image": "/article/article1.webp"
    },
    {
      "id": 2,
      "title": "The Secret to Building a Hybrid Workplace | Part III: Hiring Hybrid Employees",
      "description": "This article is a part of our series about building the ultimate hybrid workplace.",
      "tag": "PRODUCT",
      "duration": 3,
      "date": "2025-01-02T10:00:00Z",
      "image": "/article/article2.webp"
    },
    {
      "id": 3,
      "title": "Developing a Hybrid Workforce? Here Are the Top Factors to Consider",
      "description": "A recent survey conducted by global consulting firm PwC...",
      "tag": "LIFE",
      "duration": 5,
      "date": "2025-01-03T10:00:00Z",
      "image": "/article/article3.webp"
    },
    {
      "id": 4,
      "title": "Creating a Workplace Built on Collaboration",
      "description": "This article is a part of our series about building the ultimate hybrid workplace",
      "tag": "SALES",
      "duration": 9,
      "date": "2025-01-04T10:00:00Z",
      "image": "/article/article4.webp"
    }
  ]
}
